spm_calculator/__init__.py
spm_calculator/calculator.py
spm_calculator/ce_threshold.py
spm_calculator/equivalence_scale.py
spm_calculator/fcsuti_cpi.py
spm_calculator/forecast.py
spm_calculator/geoadj.py
spm_calculator-0.1.0.dist-info/licenses/LICENSE
spm_calculator-0.1.0.dist-info/METADATA
spm_calculator-0.1.0.dist-info/WHEEL
spm_calculator-0.1.0.dist-info/top_level.txt
spm_calculator-0.1.0.dist-info/RECORD
