Metadata-Version: 2.4
Name: spm-calculator
Version: 0.1.0
Summary: Calculate SPM (Supplemental Poverty Measure) thresholds for any US geography and year
Author-email: PolicyEngine <hello@policyengine.org>
License-Expression: MIT
Project-URL: Homepage, https://github.com/PolicyEngine/spm-calculator
Project-URL: Repository, https://github.com/PolicyEngine/spm-calculator
Project-URL: Issues, https://github.com/PolicyEngine/spm-calculator/issues
Classifier: Development Status :: 3 - Alpha
Classifier: Intended Audience :: Science/Research
Classifier: Programming Language :: Python :: 3
Classifier: Programming Language :: Python :: 3.10
Classifier: Programming Language :: Python :: 3.11
Classifier: Programming Language :: Python :: 3.12
Classifier: Programming Language :: Python :: 3.13
Classifier: Topic :: Scientific/Engineering
Requires-Python: >=3.10
License-File: LICENSE
Requires-Dist: pandas>=2.0
Requires-Dist: numpy>=1.24
Requires-Dist: requests>=2.28
Requires-Dist: census>=0.8
Requires-Dist: us>=3.0
Provides-Extra: dev
Requires-Dist: pytest>=7.0; extra == "dev"
Requires-Dist: pytest-cov>=4.0; extra == "dev"
Requires-Dist: black>=23.0; extra == "dev"
Requires-Dist: ruff>=0.1; extra == "dev"
Provides-Extra: app
Requires-Dist: streamlit>=1.30; extra == "app"
Dynamic: license-file
